nlp_test.py
japl/__init__.py
japl/adb.py
japl/decoradores.py
japl/exceptions.py
japl/functions.py
japl/io.py
japl/nlp.py
japl/tools.py
japl-0.0.37.dist-info/LICENSE
japl-0.0.37.dist-info/METADATA
japl-0.0.37.dist-info/WHEEL
japl-0.0.37.dist-info/top_level.txt
japl-0.0.37.dist-info/RECORD
