Metadata-Version: 2.1
Name: japl
Version: 0.0.37
Summary: Just Another Python Library is a collection of useful tools to work with.
Author-email: Juan Manuel Mejía Botero <juanmam941025@gmail.com>
License: MIT License
Project-URL: Homepage, https://github.com/Juanmam/daz
Project-URL: Documentation, https://daz.readthedocs.io/en/latest/
Keywords: decorators,Azure,Databricks
Classifier: License :: OSI Approved :: MIT License
Classifier: Programming Language :: Python
Classifier: Programming Language :: Python :: 3
Requires-Python: >=3.8s
License-File: LICENSE
Provides-Extra: dev
Requires-Dist: pandas ; extra == 'dev'
Requires-Dist: tqdm ; extra == 'dev'
Requires-Dist: pytest ; extra == 'dev'
